PKRDPNT/__init__.py
PKRDPNT/pokemon.csv
PKRDPNT/random_pokemon.py
PKRDPNT-1.0.2.dist-info/METADATA
PKRDPNT-1.0.2.dist-info/WHEEL
PKRDPNT-1.0.2.dist-info/top_level.txt
PKRDPNT-1.0.2.dist-info/RECORD
