Metadata-Version: 2.1
Name: PKRDPNT
Version: 1.0.2
Summary: Una libreria que genera un pokemon aleatorio
Author: Christopher Ruiz
Author-email: 202224135_ruiz@tesh.edu.mx
Requires-Dist: pandas
